easydatasettobop/__init__.py
easydatasettobop/__main__.py
easydatasettobop/bop_dataset_utils/__init__.py
easydatasettobop/bop_dataset_utils/inout.py
easydatasettobop/bop_dataset_utils/misc.py
easydatasettobop/bop_dataset_utils/transform.py
easydatasettobop/dataset_utils/__init__.py
easydatasettobop/dataset_utils/camera.py
easydatasettobop/dataset_utils/convert_easy_dataset_to_bop.py
easydatasettobop/dataset_utils/models.py
easydatasettobop/dataset_utils/train.py
easydatasettobop/dataset_utils/visualization_cv2.py
easydatasettobop/dataset_utils/visualization_dataset.py
EasyDataSetToBOP-1.0.2.dist-info/METADATA
EasyDataSetToBOP-1.0.2.dist-info/WHEEL
EasyDataSetToBOP-1.0.2.dist-info/top_level.txt
EasyDataSetToBOP-1.0.2.dist-info/RECORD
