Metadata-Version: 2.1
Name: EasyDataSetToBOP
Version: 1.0.2
Summary: Convert Dataset from EasyDatasetGenerator to BOP Dataset
Author: Lars Kaesberg
License: UNKNOWN
Platform: UNKNOWN
Classifier: Programming Language :: Python :: 3.9
Classifier: License :: OSI Approved :: MIT License
Classifier: Operating System :: OS Independent
Requires-Python: >=3.9
Requires-Dist: pymeshlab
Requires-Dist: imageio
Requires-Dist: pypng
Requires-Dist: opencv-python
Requires-Dist: tqdm
Requires-Dist: scipy
Requires-Dist: numpy
